{
    "1000LUNCUSDT": {
        "adg_per_exposure_long": 0.000765966901009163,
        "adg_per_exposure_short": 0.0,
        "adg_weighted_per_exposure_long": 0.000765966901009163,
        "adg_weighted_per_exposure_short": 0.0,
        "drawdown_1pct_worst_mean_long": 0.009438761884993567,
        "drawdown_1pct_worst_mean_short": -0.0,
        "drawdown_max_long": 0.03887450955759932,
        "drawdown_max_short": -0.0,
        "exposure_ratios_mean_long": 0.027246279438959197,
        "exposure_ratios_mean_short": 0.0,
        "hrs_stuck_max_long": 352.95,
        "hrs_stuck_max_short": NaN,
        "loss_profit_ratio_long": 0.0,
        "loss_profit_ratio_short": 1.0,
        "n_days": 472.9583333333333,
        "pa_distance_1pct_worst_mean_long": 0.06594448610867379,
        "pa_distance_1pct_worst_mean_short": 100.0,
        "pa_distance_max_long": 0.08290214024428423,
        "pa_distance_max_short": 100.0,
        "pa_distance_mean_long": 0.0213716692663778,
        "pa_distance_mean_short": 100.0,
        "pa_distance_std_long": 0.01559095994395672,
        "pa_distance_std_short": 1.0,
        "sharpe_ratio_long": 0.2519811509021887,
        "sharpe_ratio_short": 0.0,
        "starting_balance": 10000.0,
        "time_at_max_exposure_long": 6.16612031729079e-05,
        "time_at_max_exposure_short": 0.0,
        "timestamp_finished": 1713889468739.9731
    },
    "APTUSDT": {
        "adg_per_exposure_long": 0.000580365216772849,
        "adg_per_exposure_short": 0.0,
        "adg_weighted_per_exposure_long": 0.000580365216772849,
        "adg_weighted_per_exposure_short": 0.0,
        "drawdown_1pct_worst_mean_long": 0.07309320202801299,
        "drawdown_1pct_worst_mean_short": -0.0,
        "drawdown_max_long": 0.1767949365533242,
        "drawdown_max_short": -0.0,
        "exposure_ratios_mean_long": 0.045551815804058315,
        "exposure_ratios_mean_short": 0.0,
        "hrs_stuck_max_long": 203.11666666666667,
        "hrs_stuck_max_short": NaN,
        "loss_profit_ratio_long": 0.00852037451004563,
        "loss_profit_ratio_short": 1.0,
        "n_days": 472.9583333333333,
        "pa_distance_1pct_worst_mean_long": 0.09036168704419194,
        "pa_distance_1pct_worst_mean_short": 100.0,
        "pa_distance_max_long": 0.14790967426847051,
        "pa_distance_max_short": 100.0,
        "pa_distance_mean_long": 0.023358379013748792,
        "pa_distance_mean_short": 100.0,
        "pa_distance_std_long": 0.018322491848267862,
        "pa_distance_std_short": 1.0,
        "sharpe_ratio_long": 0.06313173341511755,
        "sharpe_ratio_short": 0.0,
        "starting_balance": 10000.0,
        "time_at_max_exposure_long": 0.007214360771230224,
        "time_at_max_exposure_short": 0.0,
        "timestamp_finished": 1713889468739.9758
    },
    "BAKEUSDT": {
        "adg_per_exposure_long": 0.0008813033037133877,
        "adg_per_exposure_short": 0.0,
        "adg_weighted_per_exposure_long": 0.0008813033037133877,
        "adg_weighted_per_exposure_short": 0.0,
        "drawdown_1pct_worst_mean_long": 0.11956964985782254,
        "drawdown_1pct_worst_mean_short": -0.0,
        "drawdown_max_long": 0.18917385623554409,
        "drawdown_max_short": -0.0,
        "exposure_ratios_mean_long": 0.04767345924851811,
        "exposure_ratios_mean_short": 0.0,
        "hrs_stuck_max_long": 156.66666666666666,
        "hrs_stuck_max_short": NaN,
        "loss_profit_ratio_long": 0.011307225545001904,
        "loss_profit_ratio_short": 1.0,
        "n_days": 472.9583333333333,
        "pa_distance_1pct_worst_mean_long": 0.138458592545641,
        "pa_distance_1pct_worst_mean_short": 100.0,
        "pa_distance_max_long": 0.14504831437778276,
        "pa_distance_max_short": 100.0,
        "pa_distance_mean_long": 0.02633091732869384,
        "pa_distance_mean_short": 100.0,
        "pa_distance_std_long": 0.02211271728884077,
        "pa_distance_std_short": 1.0,
        "sharpe_ratio_long": 0.10634011310928566,
        "sharpe_ratio_short": 0.0,
        "starting_balance": 10000.0,
        "time_at_max_exposure_long": 0.008799934012851975,
        "time_at_max_exposure_short": 0.0,
        "timestamp_finished": 1713889468739.968
    },
    "CELOUSDT": {
        "adg_per_exposure_long": 0.0005785419199875186,
        "adg_per_exposure_short": 0.0,
        "adg_weighted_per_exposure_long": 0.0005785419199875186,
        "adg_weighted_per_exposure_short": 0.0,
        "drawdown_1pct_worst_mean_long": 0.13644694809280739,
        "drawdown_1pct_worst_mean_short": -0.0,
        "drawdown_max_long": 0.21661737965659608,
        "drawdown_max_short": -0.0,
        "exposure_ratios_mean_long": 0.042478109861267474,
        "exposure_ratios_mean_short": 0.0,
        "hrs_stuck_max_long": 342.76666666666665,
        "hrs_stuck_max_short": NaN,
        "loss_profit_ratio_long": 0.018651893350408465,
        "loss_profit_ratio_short": 1.0,
        "n_days": 472.9583333333333,
        "pa_distance_1pct_worst_mean_long": 0.16090653237704342,
        "pa_distance_1pct_worst_mean_short": 100.0,
        "pa_distance_max_long": 0.1568187452977158,
        "pa_distance_max_short": 100.0,
        "pa_distance_mean_long": 0.024819187637771703,
        "pa_distance_mean_short": 100.0,
        "pa_distance_std_long": 0.022487056179189387,
        "pa_distance_std_short": 1.0,
        "sharpe_ratio_long": 0.07161578865216893,
        "sharpe_ratio_short": 0.0,
        "starting_balance": 10000.0,
        "time_at_max_exposure_long": 0.010006725195342597,
        "time_at_max_exposure_short": 0.0,
        "timestamp_finished": 1713889468739.971
    },
    "DYDXUSDT": {
        "adg_per_exposure_long": 0.0007249902031727373,
        "adg_per_exposure_short": 0.0,
        "adg_weighted_per_exposure_long": 0.0007249902031727373,
        "adg_weighted_per_exposure_short": 0.0,
        "drawdown_1pct_worst_mean_long": 0.028994867051344735,
        "drawdown_1pct_worst_mean_short": -0.0,
        "drawdown_max_long": 0.08093736104514944,
        "drawdown_max_short": -0.0,
        "exposure_ratios_mean_long": 0.03270966098090634,
        "exposure_ratios_mean_short": 0.0,
        "hrs_stuck_max_long": 252.13333333333333,
        "hrs_stuck_max_short": NaN,
        "loss_profit_ratio_long": 0.0005172706997394148,
        "loss_profit_ratio_short": 1.0,
        "n_days": 472.9583333333333,
        "pa_distance_1pct_worst_mean_long": 0.07586600623155777,
        "pa_distance_1pct_worst_mean_short": 100.0,
        "pa_distance_max_long": 0.09355028202676137,
        "pa_distance_max_short": 100.0,
        "pa_distance_mean_long": 0.022943872084315444,
        "pa_distance_mean_short": 100.0,
        "pa_distance_std_long": 0.017542261945684035,
        "pa_distance_std_short": 1.0,
        "sharpe_ratio_long": 0.1652473858147226,
        "sharpe_ratio_short": 0.0,
        "starting_balance": 10000.0,
        "time_at_max_exposure_long": 0.0014534437547245912,
        "time_at_max_exposure_short": 0.0,
        "timestamp_finished": 1713889468739.954
    },
    "FILUSDT": {
        "adg_per_exposure_long": 0.0005159676069643737,
        "adg_per_exposure_short": 0.0,
        "adg_weighted_per_exposure_long": 0.0005159676069643737,
        "adg_weighted_per_exposure_short": 0.0,
        "drawdown_1pct_worst_mean_long": 0.08716982933271428,
        "drawdown_1pct_worst_mean_short": -0.0,
        "drawdown_max_long": 0.194498298046959,
        "drawdown_max_short": -0.0,
        "exposure_ratios_mean_long": 0.03617962972787442,
        "exposure_ratios_mean_short": 0.0,
        "hrs_stuck_max_long": 308.01666666666665,
        "hrs_stuck_max_short": NaN,
        "loss_profit_ratio_long": 0.009981831649361669,
        "loss_profit_ratio_short": 1.0,
        "n_days": 472.9583333333333,
        "pa_distance_1pct_worst_mean_long": 0.09867019261250702,
        "pa_distance_1pct_worst_mean_short": 100.0,
        "pa_distance_max_long": 0.14042511457065904,
        "pa_distance_max_short": 100.0,
        "pa_distance_mean_long": 0.02044908694852118,
        "pa_distance_mean_short": 100.0,
        "pa_distance_std_long": 0.01747964406649301,
        "pa_distance_std_short": 1.0,
        "sharpe_ratio_long": 0.04880253126351231,
        "sharpe_ratio_short": 0.0,
        "starting_balance": 10000.0,
        "time_at_max_exposure_long": 0.006826775511318922,
        "time_at_max_exposure_short": 0.0,
        "timestamp_finished": 1713889468739.98
    },
    "FTMUSDT": {
        "adg_per_exposure_long": 0.0006962327772277455,
        "adg_per_exposure_short": 0.0,
        "adg_weighted_per_exposure_long": 0.0006962327772277455,
        "adg_weighted_per_exposure_short": 0.0,
        "drawdown_1pct_worst_mean_long": 0.03043712603736657,
        "drawdown_1pct_worst_mean_short": -0.0,
        "drawdown_max_long": 0.07010427786816144,
        "drawdown_max_short": -0.0,
        "exposure_ratios_mean_long": 0.03885182611355486,
        "exposure_ratios_mean_short": 0.0,
        "hrs_stuck_max_long": 227.38333333333333,
        "hrs_stuck_max_short": NaN,
        "loss_profit_ratio_long": 0.0005480548416863443,
        "loss_profit_ratio_short": 1.0,
        "n_days": 472.9583333333333,
        "pa_distance_1pct_worst_mean_long": 0.07868437855497953,
        "pa_distance_1pct_worst_mean_short": 100.0,
        "pa_distance_max_long": 0.10446649074593799,
        "pa_distance_max_short": 100.0,
        "pa_distance_mean_long": 0.023995709882370757,
        "pa_distance_mean_short": 100.0,
        "pa_distance_std_long": 0.01884059813978059,
        "pa_distance_std_short": 1.0,
        "sharpe_ratio_long": 0.14896759606917293,
        "sharpe_ratio_short": 0.0,
        "starting_balance": 10000.0,
        "time_at_max_exposure_long": 0.001250842104332013,
        "time_at_max_exposure_short": 0.0,
        "timestamp_finished": 1713889468739.967
    },
    "GALAUSDT": {
        "adg_per_exposure_long": 0.0007452438910251491,
        "adg_per_exposure_short": 0.0,
        "adg_weighted_per_exposure_long": 0.0007452438910251491,
        "adg_weighted_per_exposure_short": 0.0,
        "drawdown_1pct_worst_mean_long": 0.11565760600992057,
        "drawdown_1pct_worst_mean_short": -0.0,
        "drawdown_max_long": 0.15297069967115695,
        "drawdown_max_short": -0.0,
        "exposure_ratios_mean_long": 0.09096025545653345,
        "exposure_ratios_mean_short": 0.0,
        "hrs_stuck_max_long": 219.9,
        "hrs_stuck_max_short": NaN,
        "loss_profit_ratio_long": 0.041229326571274455,
        "loss_profit_ratio_short": 1.0,
        "n_days": 472.9583333333333,
        "pa_distance_1pct_worst_mean_long": 0.12640762319436302,
        "pa_distance_1pct_worst_mean_short": 100.0,
        "pa_distance_max_long": 0.14282628454023846,
        "pa_distance_max_short": 100.0,
        "pa_distance_mean_long": 0.0269878242222371,
        "pa_distance_mean_short": 100.0,
        "pa_distance_std_long": 0.02296363266600356,
        "pa_distance_std_short": 1.0,
        "sharpe_ratio_long": 0.07567347230031878,
        "sharpe_ratio_short": 0.0,
        "starting_balance": 10000.0,
        "time_at_max_exposure_long": 0.05368019961888232,
        "time_at_max_exposure_short": 0.0,
        "timestamp_finished": 1713889468739.995
    },
    "GMTUSDT": {
        "adg_per_exposure_long": 0.0003613770514143688,
        "adg_per_exposure_short": 0.0,
        "adg_weighted_per_exposure_long": 0.0003613770514143688,
        "adg_weighted_per_exposure_short": 0.0,
        "drawdown_1pct_worst_mean_long": 0.28519430518042904,
        "drawdown_1pct_worst_mean_short": -0.0,
        "drawdown_max_long": 0.2959089771176735,
        "drawdown_max_short": -0.0,
        "exposure_ratios_mean_long": 0.26058261275825806,
        "exposure_ratios_mean_short": 0.0,
        "hrs_stuck_max_long": 342.4,
        "hrs_stuck_max_short": NaN,
        "loss_profit_ratio_long": 0.8336278472495448,
        "loss_profit_ratio_short": 1.0,
        "n_days": 472.9583333333333,
        "pa_distance_1pct_worst_mean_long": 0.2839448177347267,
        "pa_distance_1pct_worst_mean_short": 100.0,
        "pa_distance_max_long": 0.2510730591193862,
        "pa_distance_max_short": 100.0,
        "pa_distance_mean_long": 0.06648512927520024,
        "pa_distance_mean_short": 100.0,
        "pa_distance_std_long": 0.05946528966834317,
        "pa_distance_std_short": 1.0,
        "sharpe_ratio_long": 0.032207819900553755,
        "sharpe_ratio_short": 0.0,
        "starting_balance": 10000.0,
        "time_at_max_exposure_long": 0.20064464337841786,
        "time_at_max_exposure_short": 0.0,
        "timestamp_finished": 1713889468740.0032
    },
    "GRTUSDT": {
        "adg_per_exposure_long": 0.0006063087342480511,
        "adg_per_exposure_short": 0.0,
        "adg_weighted_per_exposure_long": 0.0006063087342480511,
        "adg_weighted_per_exposure_short": 0.0,
        "drawdown_1pct_worst_mean_long": 0.010601101144459583,
        "drawdown_1pct_worst_mean_short": -0.0,
        "drawdown_max_long": 0.029535760824796992,
        "drawdown_max_short": -0.0,
        "exposure_ratios_mean_long": 0.02884400747404973,
        "exposure_ratios_mean_short": 0.0,
        "hrs_stuck_max_long": 254.35,
        "hrs_stuck_max_short": NaN,
        "loss_profit_ratio_long": 0.0,
        "loss_profit_ratio_short": 1.0,
        "n_days": 472.9583333333333,
        "pa_distance_1pct_worst_mean_long": 0.07291286298917658,
        "pa_distance_1pct_worst_mean_short": 100.0,
        "pa_distance_max_long": 0.08929574888907418,
        "pa_distance_max_short": 100.0,
        "pa_distance_mean_long": 0.02397940383602937,
        "pa_distance_mean_short": 100.0,
        "pa_distance_std_long": 0.01748418224390543,
        "pa_distance_std_short": 1.0,
        "sharpe_ratio_long": 0.23889295616860448,
        "sharpe_ratio_short": 0.0,
        "starting_balance": 10000.0,
        "time_at_max_exposure_long": 6.16612031729079e-05,
        "time_at_max_exposure_short": 0.0,
        "timestamp_finished": 1713889468739.9658
    },
    "IMXUSDT": {
        "adg_per_exposure_long": 0.0006337950477912635,
        "adg_per_exposure_short": 0.0,
        "adg_weighted_per_exposure_long": 0.0006337950477912635,
        "adg_weighted_per_exposure_short": 0.0,
        "drawdown_1pct_worst_mean_long": 0.0522870843945185,
        "drawdown_1pct_worst_mean_short": -0.0,
        "drawdown_max_long": 0.09408301142511737,
        "drawdown_max_short": -0.0,
        "exposure_ratios_mean_long": 0.046551959338282614,
        "exposure_ratios_mean_short": 0.0,
        "hrs_stuck_max_long": 248.76666666666668,
        "hrs_stuck_max_short": NaN,
        "loss_profit_ratio_long": 0.007722344946200966,
        "loss_profit_ratio_short": 1.0,
        "n_days": 472.9583333333333,
        "pa_distance_1pct_worst_mean_long": 0.08461388025735915,
        "pa_distance_1pct_worst_mean_short": 100.0,
        "pa_distance_max_long": 0.10774233185313471,
        "pa_distance_max_short": 100.0,
        "pa_distance_mean_long": 0.025355744514319028,
        "pa_distance_mean_short": 100.0,
        "pa_distance_std_long": 0.019372844933658463,
        "pa_distance_std_short": 1.0,
        "sharpe_ratio_long": 0.12320628157444788,
        "sharpe_ratio_short": 0.0,
        "starting_balance": 10000.0,
        "time_at_max_exposure_long": 0.015494498562079208,
        "time_at_max_exposure_short": 0.0,
        "timestamp_finished": 1713889468739.982
    },
    "INJUSDT": {
        "adg_per_exposure_long": 0.0007781385564706866,
        "adg_per_exposure_short": 0.0,
        "adg_weighted_per_exposure_long": 0.0007781385564706866,
        "adg_weighted_per_exposure_short": 0.0,
        "drawdown_1pct_worst_mean_long": 0.016584929810682686,
        "drawdown_1pct_worst_mean_short": -0.0,
        "drawdown_max_long": 0.04361698767560659,
        "drawdown_max_short": -0.0,
        "exposure_ratios_mean_long": 0.02592330068250997,
        "exposure_ratios_mean_short": 0.0,
        "hrs_stuck_max_long": 255.38333333333333,
        "hrs_stuck_max_short": NaN,
        "loss_profit_ratio_long": 0.0,
        "loss_profit_ratio_short": 1.0,
        "n_days": 472.9583333333333,
        "pa_distance_1pct_worst_mean_long": 0.07283752487420066,
        "pa_distance_1pct_worst_mean_short": 100.0,
        "pa_distance_max_long": 0.09183404607958189,
        "pa_distance_max_short": 100.0,
        "pa_distance_mean_long": 0.022506039195804652,
        "pa_distance_mean_short": 100.0,
        "pa_distance_std_long": 0.017650927742643683,
        "pa_distance_std_short": 1.0,
        "sharpe_ratio_long": 0.2045237562117604,
        "sharpe_ratio_short": 0.0,
        "starting_balance": 10000.0,
        "time_at_max_exposure_long": 7.927924404676272e-05,
        "time_at_max_exposure_short": 0.0,
        "timestamp_finished": 1713889468739.97
    },
    "JASMYUSDT": {
        "adg_per_exposure_long": 0.0006509822984055447,
        "adg_per_exposure_short": 0.0,
        "adg_weighted_per_exposure_long": 0.0006509822984055447,
        "adg_weighted_per_exposure_short": 0.0,
        "drawdown_1pct_worst_mean_long": 0.03867639058014908,
        "drawdown_1pct_worst_mean_short": -0.0,
        "drawdown_max_long": 0.08875346316200315,
        "drawdown_max_short": -0.0,
        "exposure_ratios_mean_long": 0.03689710368008704,
        "exposure_ratios_mean_short": 0.0,
        "hrs_stuck_max_long": 300.3833333333333,
        "hrs_stuck_max_short": NaN,
        "loss_profit_ratio_long": 0.00713019790531807,
        "loss_profit_ratio_short": 1.0,
        "n_days": 472.9583333333333,
        "pa_distance_1pct_worst_mean_long": 0.07291527165574065,
        "pa_distance_1pct_worst_mean_short": 100.0,
        "pa_distance_max_long": 0.11532505653275207,
        "pa_distance_max_short": 100.0,
        "pa_distance_mean_long": 0.022487749786325603,
        "pa_distance_mean_short": 100.0,
        "pa_distance_std_long": 0.017040836173811906,
        "pa_distance_std_short": 1.0,
        "sharpe_ratio_long": 0.11245667686327052,
        "sharpe_ratio_short": 0.0,
        "starting_balance": 10000.0,
        "time_at_max_exposure_long": 0.010843506481312928,
        "time_at_max_exposure_short": 0.0,
        "timestamp_finished": 1713889468739.9768
    },
    "LDOUSDT": {
        "adg_per_exposure_long": 0.0005762247953107202,
        "adg_per_exposure_short": 0.0,
        "adg_weighted_per_exposure_long": 0.0005762247953107202,
        "adg_weighted_per_exposure_short": 0.0,
        "drawdown_1pct_worst_mean_long": 0.0795623143179983,
        "drawdown_1pct_worst_mean_short": -0.0,
        "drawdown_max_long": 0.2187141721918152,
        "drawdown_max_short": -0.0,
        "exposure_ratios_mean_long": 0.03800868105990753,
        "exposure_ratios_mean_short": 0.0,
        "hrs_stuck_max_long": 228.66666666666666,
        "hrs_stuck_max_short": NaN,
        "loss_profit_ratio_long": 0.00673908132332655,
        "loss_profit_ratio_short": 1.0,
        "n_days": 472.9583333333333,
        "pa_distance_1pct_worst_mean_long": 0.10249846553587112,
        "pa_distance_1pct_worst_mean_short": 100.0,
        "pa_distance_max_long": 0.17478178890300414,
        "pa_distance_max_short": 100.0,
        "pa_distance_mean_long": 0.026653560804277526,
        "pa_distance_mean_short": 100.0,
        "pa_distance_std_long": 0.020153904830369038,
        "pa_distance_std_short": 1.0,
        "sharpe_ratio_long": 0.036202009694736165,
        "sharpe_ratio_short": 0.0,
        "starting_balance": 10000.0,
        "time_at_max_exposure_long": 0.0057168738542065795,
        "time_at_max_exposure_short": 0.0,
        "timestamp_finished": 1713889468739.964
    },
    "LINAUSDT": {
        "adg_per_exposure_long": 0.0005168871094056726,
        "adg_per_exposure_short": 0.0,
        "adg_weighted_per_exposure_long": 0.0005168871094056726,
        "adg_weighted_per_exposure_short": 0.0,
        "drawdown_1pct_worst_mean_long": 0.35835912764986244,
        "drawdown_1pct_worst_mean_short": -0.0,
        "drawdown_max_long": 0.4769271677695018,
        "drawdown_max_short": -0.0,
        "exposure_ratios_mean_long": 0.08109617142369605,
        "exposure_ratios_mean_short": 0.0,
        "hrs_stuck_max_long": 346.46666666666664,
        "hrs_stuck_max_short": NaN,
        "loss_profit_ratio_long": 0.18729997242157115,
        "loss_profit_ratio_short": 1.0,
        "n_days": 472.9583333333333,
        "pa_distance_1pct_worst_mean_long": 0.5431704939959542,
        "pa_distance_1pct_worst_mean_short": 100.0,
        "pa_distance_max_long": 0.6392112216985159,
        "pa_distance_max_short": 100.0,
        "pa_distance_mean_long": 0.048082765604178325,
        "pa_distance_mean_short": 100.0,
        "pa_distance_std_long": 0.08295388976433286,
        "pa_distance_std_short": 1.0,
        "sharpe_ratio_long": 0.010092100326042755,
        "sharpe_ratio_short": 0.0,
        "starting_balance": 10000.0,
        "time_at_max_exposure_long": 0.05314302978158906,
        "time_at_max_exposure_short": 0.0,
        "timestamp_finished": 1713889468739.9932
    },
    "LUNA2USDT": {
        "adg_per_exposure_long": 0.0006093016529491457,
        "adg_per_exposure_short": 0.0,
        "adg_weighted_per_exposure_long": 0.0006093016529491457,
        "adg_weighted_per_exposure_short": 0.0,
        "drawdown_1pct_worst_mean_long": 0.2998973758432542,
        "drawdown_1pct_worst_mean_short": -0.0,
        "drawdown_max_long": 0.39749472481814335,
        "drawdown_max_short": -0.0,
        "exposure_ratios_mean_long": 0.10575787469231827,
        "exposure_ratios_mean_short": 0.0,
        "hrs_stuck_max_long": 352.95,
        "hrs_stuck_max_short": NaN,
        "loss_profit_ratio_long": 0.11575003991126738,
        "loss_profit_ratio_short": 1.0,
        "n_days": 472.9583333333333,
        "pa_distance_1pct_worst_mean_long": 0.40264602087981616,
        "pa_distance_1pct_worst_mean_short": 100.0,
        "pa_distance_max_long": 0.35183249833409275,
        "pa_distance_max_short": 100.0,
        "pa_distance_mean_long": 0.03450043817501087,
        "pa_distance_mean_short": 100.0,
        "pa_distance_std_long": 0.04907655588116058,
        "pa_distance_std_short": 1.0,
        "sharpe_ratio_long": 0.0013421092603851793,
        "sharpe_ratio_short": 0.0,
        "starting_balance": 10000.0,
        "time_at_max_exposure_long": 0.06743064792644078,
        "time_at_max_exposure_short": 0.0,
        "timestamp_finished": 1713889468739.989
    },
    "MASKUSDT": {
        "adg_per_exposure_long": 0.0006599388929420247,
        "adg_per_exposure_short": 0.0,
        "adg_weighted_per_exposure_long": 0.0006599388929420247,
        "adg_weighted_per_exposure_short": 0.0,
        "drawdown_1pct_worst_mean_long": 0.1271370658270632,
        "drawdown_1pct_worst_mean_short": -0.0,
        "drawdown_max_long": 0.15387925240222242,
        "drawdown_max_short": -0.0,
        "exposure_ratios_mean_long": 0.109069201751032,
        "exposure_ratios_mean_short": 0.0,
        "hrs_stuck_max_long": 383.1,
        "hrs_stuck_max_short": NaN,
        "loss_profit_ratio_long": 0.060486856868038154,
        "loss_profit_ratio_short": 1.0,
        "n_days": 472.9583333333333,
        "pa_distance_1pct_worst_mean_long": 0.14757900293993637,
        "pa_distance_1pct_worst_mean_short": 100.0,
        "pa_distance_max_long": 0.1461219123307881,
        "pa_distance_max_short": 100.0,
        "pa_distance_mean_long": 0.03157360715224031,
        "pa_distance_mean_short": 100.0,
        "pa_distance_std_long": 0.028399557531059744,
        "pa_distance_std_short": 1.0,
        "sharpe_ratio_long": 0.07272018613812856,
        "sharpe_ratio_short": 0.0,
        "starting_balance": 10000.0,
        "time_at_max_exposure_long": 0.05832238849886843,
        "time_at_max_exposure_short": 0.0,
        "timestamp_finished": 1713889468739.9958
    },
    "MTLUSDT": {
        "adg_per_exposure_long": 0.0006133350184840403,
        "adg_per_exposure_short": 0.0,
        "adg_weighted_per_exposure_long": 0.0006133350184840403,
        "adg_weighted_per_exposure_short": 0.0,
        "drawdown_1pct_worst_mean_long": 0.1444503890735969,
        "drawdown_1pct_worst_mean_short": -0.0,
        "drawdown_max_long": 0.21266802115202046,
        "drawdown_max_short": -0.0,
        "exposure_ratios_mean_long": 0.04530706312980943,
        "exposure_ratios_mean_short": 0.0,
        "hrs_stuck_max_long": 277.1166666666667,
        "hrs_stuck_max_short": NaN,
        "loss_profit_ratio_long": 0.03649189436684217,
        "loss_profit_ratio_short": 1.0,
        "n_days": 472.9583333333333,
        "pa_distance_1pct_worst_mean_long": 0.16243328063771464,
        "pa_distance_1pct_worst_mean_short": 100.0,
        "pa_distance_max_long": 0.18958833295373567,
        "pa_distance_max_short": 100.0,
        "pa_distance_mean_long": 0.025499327722562536,
        "pa_distance_mean_short": 100.0,
        "pa_distance_std_long": 0.02592015661638058,
        "pa_distance_std_short": 1.0,
        "sharpe_ratio_long": 0.08225736954628524,
        "sharpe_ratio_short": 0.0,
        "starting_balance": 10000.0,
        "time_at_max_exposure_long": 0.016172767917210028,
        "time_at_max_exposure_short": 0.0,
        "timestamp_finished": 1713889468739.991
    },
    "NEARUSDT": {
        "adg_per_exposure_long": 0.0006180795937826833,
        "adg_per_exposure_short": 0.0,
        "adg_weighted_per_exposure_long": 0.0006180795937826833,
        "adg_weighted_per_exposure_short": 0.0,
        "drawdown_1pct_worst_mean_long": 0.0792754145844534,
        "drawdown_1pct_worst_mean_short": -0.0,
        "drawdown_max_long": 0.13349877921596154,
        "drawdown_max_short": -0.0,
        "exposure_ratios_mean_long": 0.04598448154381506,
        "exposure_ratios_mean_short": 0.0,
        "hrs_stuck_max_long": 503.1166666666667,
        "hrs_stuck_max_short": NaN,
        "loss_profit_ratio_long": 0.008089524418732915,
        "loss_profit_ratio_short": 1.0,
        "n_days": 472.9583333333333,
        "pa_distance_1pct_worst_mean_long": 0.10149873551921684,
        "pa_distance_1pct_worst_mean_short": 100.0,
        "pa_distance_max_long": 0.12513546450062576,
        "pa_distance_max_short": 100.0,
        "pa_distance_mean_long": 0.025294473841234455,
        "pa_distance_mean_short": 100.0,
        "pa_distance_std_long": 0.019673273557914046,
        "pa_distance_std_short": 1.0,
        "sharpe_ratio_long": 0.11019142647240493,
        "sharpe_ratio_short": 0.0,
        "starting_balance": 10000.0,
        "time_at_max_exposure_long": 0.00695009403789357,
        "time_at_max_exposure_short": 0.0,
        "timestamp_finished": 1713889468739.9832
    },
    "OCEANUSDT": {
        "adg_per_exposure_long": 0.000636088613130914,
        "adg_per_exposure_short": 0.0,
        "adg_weighted_per_exposure_long": 0.000636088613130914,
        "adg_weighted_per_exposure_short": 0.0,
        "drawdown_1pct_worst_mean_long": 0.016756152837333567,
        "drawdown_1pct_worst_mean_short": -0.0,
        "drawdown_max_long": 0.04774791060163645,
        "drawdown_max_short": -0.0,
        "exposure_ratios_mean_long": 0.02596781263504358,
        "exposure_ratios_mean_short": 0.0,
        "hrs_stuck_max_long": 352.95,
        "hrs_stuck_max_short": NaN,
        "loss_profit_ratio_long": 0.0,
        "loss_profit_ratio_short": 1.0,
        "n_days": 472.9583333333333,
        "pa_distance_1pct_worst_mean_long": 0.0734326754309137,
        "pa_distance_1pct_worst_mean_short": 100.0,
        "pa_distance_max_long": 0.09631763944678329,
        "pa_distance_max_short": 100.0,
        "pa_distance_mean_long": 0.023000490691711756,
        "pa_distance_mean_short": 100.0,
        "pa_distance_std_long": 0.016816276299182198,
        "pa_distance_std_short": 1.0,
        "sharpe_ratio_long": 0.18842134887413775,
        "sharpe_ratio_short": 0.0,
        "starting_balance": 10000.0,
        "time_at_max_exposure_long": 0.0004844786650607518,
        "time_at_max_exposure_short": 0.0,
        "timestamp_finished": 1713889468739.979
    },
    "OPUSDT": {
        "adg_per_exposure_long": 0.0007583769084789083,
        "adg_per_exposure_short": 0.0,
        "adg_weighted_per_exposure_long": 0.0007583769084789083,
        "adg_weighted_per_exposure_short": 0.0,
        "drawdown_1pct_worst_mean_long": 0.04685135853188299,
        "drawdown_1pct_worst_mean_short": -0.0,
        "drawdown_max_long": 0.1045181253802859,
        "drawdown_max_short": -0.0,
        "exposure_ratios_mean_long": 0.04168671303267614,
        "exposure_ratios_mean_short": 0.0,
        "hrs_stuck_max_long": 200.06666666666666,
        "hrs_stuck_max_short": NaN,
        "loss_profit_ratio_long": 0.003360162016614396,
        "loss_profit_ratio_short": 1.0,
        "n_days": 472.9583333333333,
        "pa_distance_1pct_worst_mean_long": 0.08357958091021317,
        "pa_distance_1pct_worst_mean_short": 100.0,
        "pa_distance_max_long": 0.11811329247536687,
        "pa_distance_max_short": 100.0,
        "pa_distance_mean_long": 0.02435025796559614,
        "pa_distance_mean_short": 100.0,
        "pa_distance_std_long": 0.01843613017072538,
        "pa_distance_std_short": 1.0,
        "sharpe_ratio_long": 0.11706227624595252,
        "sharpe_ratio_short": 0.0,
        "starting_balance": 10000.0,
        "time_at_max_exposure_long": 0.006377521288692375,
        "time_at_max_exposure_short": 0.0,
        "timestamp_finished": 1713889468739.985
    },
    "PEOPLEUSDT": {
        "adg_per_exposure_long": 0.0008753538702674923,
        "adg_per_exposure_short": 0.0,
        "adg_weighted_per_exposure_long": 0.0008753538702674923,
        "adg_weighted_per_exposure_short": 0.0,
        "drawdown_1pct_worst_mean_long": 0.018170062188696705,
        "drawdown_1pct_worst_mean_short": -0.0,
        "drawdown_max_long": 0.06318681233518174,
        "drawdown_max_short": -0.0,
        "exposure_ratios_mean_long": 0.035971773519056525,
        "exposure_ratios_mean_short": 0.0,
        "hrs_stuck_max_long": 244.11666666666667,
        "hrs_stuck_max_short": NaN,
        "loss_profit_ratio_long": 0.0,
        "loss_profit_ratio_short": 1.0,
        "n_days": 472.9583333333333,
        "pa_distance_1pct_worst_mean_long": 0.07294337112058767,
        "pa_distance_1pct_worst_mean_short": 100.0,
        "pa_distance_max_long": 0.09608634112140144,
        "pa_distance_max_short": 100.0,
        "pa_distance_mean_long": 0.022299359222498365,
        "pa_distance_mean_short": 100.0,
        "pa_distance_std_long": 0.016855598677461517,
        "pa_distance_std_short": 1.0,
        "sharpe_ratio_long": 0.19795487201229123,
        "sharpe_ratio_short": 0.0,
        "starting_balance": 10000.0,
        "time_at_max_exposure_long": 0.0005549508285561711,
        "time_at_max_exposure_short": 0.0,
        "timestamp_finished": 1713889468739.974
    },
    "SNXUSDT": {
        "adg_per_exposure_long": 0.0006027358955171813,
        "adg_per_exposure_short": 0.0,
        "adg_weighted_per_exposure_long": 0.0006027358955171813,
        "adg_weighted_per_exposure_short": 0.0,
        "drawdown_1pct_worst_mean_long": 0.024123264151980003,
        "drawdown_1pct_worst_mean_short": -0.0,
        "drawdown_max_long": 0.060887853448086164,
        "drawdown_max_short": -0.0,
        "exposure_ratios_mean_long": 0.02927377732864892,
        "exposure_ratios_mean_short": 0.0,
        "hrs_stuck_max_long": 289.95,
        "hrs_stuck_max_short": NaN,
        "loss_profit_ratio_long": 0.0007431790700640274,
        "loss_profit_ratio_short": 1.0,
        "n_days": 472.9583333333333,
        "pa_distance_1pct_worst_mean_long": 0.07810883274095187,
        "pa_distance_1pct_worst_mean_short": 100.0,
        "pa_distance_max_long": 0.10150964876762861,
        "pa_distance_max_short": 100.0,
        "pa_distance_mean_long": 0.024635011547851915,
        "pa_distance_mean_short": 100.0,
        "pa_distance_std_long": 0.019413161770738967,
        "pa_distance_std_short": 1.0,
        "sharpe_ratio_long": 0.16193838766837962,
        "sharpe_ratio_short": 0.0,
        "starting_balance": 10000.0,
        "time_at_max_exposure_long": 0.0011099016571123421,
        "time_at_max_exposure_short": 0.0,
        "timestamp_finished": 1713889468739.9858
    },
    "SOLUSDT": {
        "adg_per_exposure_long": 0.0004972492300425735,
        "adg_per_exposure_short": 0.0,
        "adg_weighted_per_exposure_long": 0.0004972492300425735,
        "adg_weighted_per_exposure_short": 0.0,
        "drawdown_1pct_worst_mean_long": 0.02212596162079192,
        "drawdown_1pct_worst_mean_short": -0.0,
        "drawdown_max_long": 0.10788748938996427,
        "drawdown_max_short": -0.0,
        "exposure_ratios_mean_long": 0.031016536565660092,
        "exposure_ratios_mean_short": 0.0,
        "hrs_stuck_max_long": 315.06666666666666,
        "hrs_stuck_max_short": NaN,
        "loss_profit_ratio_long": 0.004508189176390548,
        "loss_profit_ratio_short": 1.0,
        "n_days": 472.9583333333333,
        "pa_distance_1pct_worst_mean_long": 0.07077362909895858,
        "pa_distance_1pct_worst_mean_short": 100.0,
        "pa_distance_max_long": 0.11904408894129306,
        "pa_distance_max_short": 100.0,
        "pa_distance_mean_long": 0.021238720172068324,
        "pa_distance_mean_short": 100.0,
        "pa_distance_std_long": 0.016251018493613784,
        "pa_distance_std_short": 1.0,
        "sharpe_ratio_long": 0.1947372592245177,
        "sharpe_ratio_short": 0.0,
        "starting_balance": 10000.0,
        "time_at_max_exposure_long": 0.004166513415705531,
        "time_at_max_exposure_short": 0.0,
        "timestamp_finished": 1713889468739.9868
    },
    "STMXUSDT": {
        "adg_per_exposure_long": 0.000583069499878075,
        "adg_per_exposure_short": 0.0,
        "adg_weighted_per_exposure_long": 0.000583069499878075,
        "adg_weighted_per_exposure_short": 0.0,
        "drawdown_1pct_worst_mean_long": 0.145202502085482,
        "drawdown_1pct_worst_mean_short": -0.0,
        "drawdown_max_long": 0.17800139666800752,
        "drawdown_max_short": -0.0,
        "exposure_ratios_mean_long": 0.08267613842975932,
        "exposure_ratios_mean_short": 0.0,
        "hrs_stuck_max_long": 287.18333333333334,
        "hrs_stuck_max_short": NaN,
        "loss_profit_ratio_long": 0.07469224433755484,
        "loss_profit_ratio_short": 1.0,
        "n_days": 472.9583333333333,
        "pa_distance_1pct_worst_mean_long": 0.15820993835668817,
        "pa_distance_1pct_worst_mean_short": 100.0,
        "pa_distance_max_long": 0.16280934504140657,
        "pa_distance_max_short": 100.0,
        "pa_distance_mean_long": 0.02869954271791632,
        "pa_distance_mean_short": 100.0,
        "pa_distance_std_long": 0.027822273569512883,
        "pa_distance_std_short": 1.0,
        "sharpe_ratio_long": 0.07142118346046143,
        "sharpe_ratio_short": 0.0,
        "starting_balance": 10000.0,
        "time_at_max_exposure_long": 0.03545500559540597,
        "time_at_max_exposure_short": 0.0,
        "timestamp_finished": 1713889468740.0
    },
    "STORJUSDT": {
        "adg_per_exposure_long": 0.00019435884085350352,
        "adg_per_exposure_short": 0.0,
        "adg_weighted_per_exposure_long": 0.00019435884085350352,
        "adg_weighted_per_exposure_short": 0.0,
        "drawdown_1pct_worst_mean_long": 0.36304262442384905,
        "drawdown_1pct_worst_mean_short": -0.0,
        "drawdown_max_long": 0.4131543332781771,
        "drawdown_max_short": -0.0,
        "exposure_ratios_mean_long": 0.25014151847346977,
        "exposure_ratios_mean_short": 0.0,
        "hrs_stuck_max_long": 421.98333333333335,
        "hrs_stuck_max_short": NaN,
        "loss_profit_ratio_long": 0.5767366412677836,
        "loss_profit_ratio_short": 1.0,
        "n_days": 472.9583333333333,
        "pa_distance_1pct_worst_mean_long": 0.46700589271933685,
        "pa_distance_1pct_worst_mean_short": 100.0,
        "pa_distance_max_long": 0.46244046764874513,
        "pa_distance_max_short": 100.0,
        "pa_distance_mean_long": 0.07781526716716491,
        "pa_distance_mean_short": 100.0,
        "pa_distance_std_long": 0.09354830386460972,
        "pa_distance_std_short": 1.0,
        "sharpe_ratio_long": 0.019710140777244558,
        "sharpe_ratio_short": 0.0,
        "starting_balance": 10000.0,
        "time_at_max_exposure_long": 0.18876231264779017,
        "time_at_max_exposure_short": 0.0,
        "timestamp_finished": 1713889468740.0042
    },
    "TRBUSDT": {
        "adg_per_exposure_long": 0.0011896522464167614,
        "adg_per_exposure_short": 0.0,
        "adg_weighted_per_exposure_long": 0.0011896522464167614,
        "adg_weighted_per_exposure_short": 0.0,
        "drawdown_1pct_worst_mean_long": 0.11388237357629125,
        "drawdown_1pct_worst_mean_short": -0.0,
        "drawdown_max_long": 0.18158396869448676,
        "drawdown_max_short": -0.0,
        "exposure_ratios_mean_long": 0.06920309112273434,
        "exposure_ratios_mean_short": 0.0,
        "hrs_stuck_max_long": 260.95,
        "hrs_stuck_max_short": NaN,
        "loss_profit_ratio_long": 0.025857362445258925,
        "loss_profit_ratio_short": 1.0,
        "n_days": 472.9583333333333,
        "pa_distance_1pct_worst_mean_long": 0.12787463448762462,
        "pa_distance_1pct_worst_mean_short": 100.0,
        "pa_distance_max_long": 0.21651074523481012,
        "pa_distance_max_short": 100.0,
        "pa_distance_mean_long": 0.02653122663977108,
        "pa_distance_mean_short": 100.0,
        "pa_distance_std_long": 0.02609051112703567,
        "pa_distance_std_short": 1.0,
        "sharpe_ratio_long": 0.10670707714442654,
        "sharpe_ratio_short": 0.0,
        "starting_balance": 10000.0,
        "time_at_max_exposure_long": 0.023898016955841532,
        "time_at_max_exposure_short": 0.0,
        "timestamp_finished": 1713889468739.999
    },
    "UNFIUSDT": {
        "adg_per_exposure_long": 0.00015524643290354412,
        "adg_per_exposure_short": 0.0,
        "adg_weighted_per_exposure_long": 0.00015524643290354412,
        "adg_weighted_per_exposure_short": 0.0,
        "drawdown_1pct_worst_mean_long": 0.49282777640293124,
        "drawdown_1pct_worst_mean_short": -0.0,
        "drawdown_max_long": 0.5837919257046588,
        "drawdown_max_short": -0.0,
        "exposure_ratios_mean_long": 0.21238228693608202,
        "exposure_ratios_mean_short": 0.0,
        "hrs_stuck_max_long": 180.13333333333333,
        "hrs_stuck_max_short": NaN,
        "loss_profit_ratio_long": 0.6995068917552991,
        "loss_profit_ratio_short": 1.0,
        "n_days": 472.9583333333333,
        "pa_distance_1pct_worst_mean_long": 0.689889388679527,
        "pa_distance_1pct_worst_mean_short": 100.0,
        "pa_distance_max_long": 0.608873842764807,
        "pa_distance_max_short": 100.0,
        "pa_distance_mean_long": 0.08296206274963738,
        "pa_distance_mean_short": 100.0,
        "pa_distance_std_long": 0.09291104482193455,
        "pa_distance_std_short": 1.0,
        "sharpe_ratio_long": -0.019835168916681512,
        "sharpe_ratio_short": 0.0,
        "starting_balance": 10000.0,
        "time_at_max_exposure_long": 0.17104768875047935,
        "time_at_max_exposure_short": 0.0,
        "timestamp_finished": 1713889468740.002
    },
    "WAVESUSDT": {
        "adg_per_exposure_long": 0.0005697681249055009,
        "adg_per_exposure_short": 0.0,
        "adg_weighted_per_exposure_long": 0.0005697681249055009,
        "adg_weighted_per_exposure_short": 0.0,
        "drawdown_1pct_worst_mean_long": 0.021671166974955188,
        "drawdown_1pct_worst_mean_short": -0.0,
        "drawdown_max_long": 0.052715570797228495,
        "drawdown_max_short": -0.0,
        "exposure_ratios_mean_long": 0.027209934195500975,
        "exposure_ratios_mean_short": 0.0,
        "hrs_stuck_max_long": 225.76666666666668,
        "hrs_stuck_max_short": NaN,
        "loss_profit_ratio_long": 0.0,
        "loss_profit_ratio_short": 1.0,
        "n_days": 472.9583333333333,
        "pa_distance_1pct_worst_mean_long": 0.071404385885211,
        "pa_distance_1pct_worst_mean_short": 100.0,
        "pa_distance_max_long": 0.09464542921139499,
        "pa_distance_max_short": 100.0,
        "pa_distance_mean_long": 0.01861500358100848,
        "pa_distance_mean_short": 100.0,
        "pa_distance_std_long": 0.015452939216656001,
        "pa_distance_std_short": 1.0,
        "sharpe_ratio_long": 0.2000228783645385,
        "sharpe_ratio_short": 0.0,
        "starting_balance": 10000.0,
        "time_at_max_exposure_long": 0.0,
        "time_at_max_exposure_short": 0.0,
        "timestamp_finished": 1713889468739.998
    },
    "WOOUSDT": {
        "adg_per_exposure_long": 0.0007204651162318054,
        "adg_per_exposure_short": 0.0,
        "adg_weighted_per_exposure_long": 0.0007204651162318054,
        "adg_weighted_per_exposure_short": 0.0,
        "drawdown_1pct_worst_mean_long": 0.035799662819720086,
        "drawdown_1pct_worst_mean_short": -0.0,
        "drawdown_max_long": 0.0629167130423641,
        "drawdown_max_short": -0.0,
        "exposure_ratios_mean_long": 0.0464238100583519,
        "exposure_ratios_mean_short": 0.0,
        "hrs_stuck_max_long": 260.6333333333333,
        "hrs_stuck_max_short": NaN,
        "loss_profit_ratio_long": 0.00026068973668428826,
        "loss_profit_ratio_short": 1.0,
        "n_days": 472.9583333333333,
        "pa_distance_1pct_worst_mean_long": 0.0838721747687715,
        "pa_distance_1pct_worst_mean_short": 100.0,
        "pa_distance_max_long": 0.1049959220311351,
        "pa_distance_max_short": 100.0,
        "pa_distance_mean_long": 0.025749511792924777,
        "pa_distance_mean_short": 100.0,
        "pa_distance_std_long": 0.01982548727693024,
        "pa_distance_std_short": 1.0,
        "sharpe_ratio_long": 0.12204296775216739,
        "sharpe_ratio_short": 0.0,
        "starting_balance": 10000.0,
        "time_at_max_exposure_long": 0.00024664481269163157,
        "time_at_max_exposure_short": 0.0,
        "timestamp_finished": 1713889468739.99
    }
}