{
    "1000LUNCUSDT": {
        "adg_per_exposure_long": 0.0008009630345995333,
        "adg_per_exposure_short": 0.0,
        "adg_weighted_per_exposure_long": 0.0008009630345995333,
        "adg_weighted_per_exposure_short": 0.0,
        "drawdown_1pct_worst_mean_long": 0.23366579592227338,
        "drawdown_1pct_worst_mean_short": -0.0,
        "drawdown_max_long": 0.2804417127751426,
        "drawdown_max_short": -0.0,
        "exposure_ratios_mean_long": 0.163837548007033,
        "exposure_ratios_mean_short": 0.0,
        "hrs_stuck_max_long": 194.85,
        "hrs_stuck_max_short": NaN,
        "loss_profit_ratio_long": 0.475080811948581,
        "loss_profit_ratio_short": 1.0,
        "n_days": 472.9583333333333,
        "pa_distance_1pct_worst_mean_long": 0.1803766564652734,
        "pa_distance_1pct_worst_mean_short": 100.0,
        "pa_distance_max_long": 0.29255874116825853,
        "pa_distance_max_short": 100.0,
        "pa_distance_mean_long": 0.028688358420815817,
        "pa_distance_mean_short": 100.0,
        "pa_distance_std_long": 0.036690742611087436,
        "pa_distance_std_short": 1.0,
        "sharpe_ratio_long": 0.04638939389253179,
        "sharpe_ratio_short": 0.0,
        "starting_balance": 10000.0,
        "time_at_max_exposure_long": 0.11928741717270522,
        "time_at_max_exposure_short": 0.0,
        "timestamp_finished": 1714163062343.058
    },
    "APTUSDT": {
        "adg_per_exposure_long": 0.0009755701161080488,
        "adg_per_exposure_short": 0.0,
        "adg_weighted_per_exposure_long": 0.0009755701161080488,
        "adg_weighted_per_exposure_short": 0.0,
        "drawdown_1pct_worst_mean_long": 0.18814705313268462,
        "drawdown_1pct_worst_mean_short": -0.0,
        "drawdown_max_long": 0.28249988663956155,
        "drawdown_max_short": -0.0,
        "exposure_ratios_mean_long": 0.08526022853763898,
        "exposure_ratios_mean_short": 0.0,
        "hrs_stuck_max_long": 147.16666666666666,
        "hrs_stuck_max_short": NaN,
        "loss_profit_ratio_long": 0.05679418671969862,
        "loss_profit_ratio_short": 1.0,
        "n_days": 472.9583333333333,
        "pa_distance_1pct_worst_mean_long": 0.20630574462905507,
        "pa_distance_1pct_worst_mean_short": 100.0,
        "pa_distance_max_long": 0.23741011690789243,
        "pa_distance_max_short": 100.0,
        "pa_distance_mean_long": 0.017955403238173944,
        "pa_distance_mean_short": 100.0,
        "pa_distance_std_long": 0.02226098782568687,
        "pa_distance_std_short": 1.0,
        "sharpe_ratio_long": 0.05666943301722323,
        "sharpe_ratio_short": 0.0,
        "starting_balance": 10000.0,
        "time_at_max_exposure_long": 0.016956784315295657,
        "time_at_max_exposure_short": 0.0,
        "timestamp_finished": 1714163062343.033
    },
    "BAKEUSDT": {
        "adg_per_exposure_long": 0.0013139757156326315,
        "adg_per_exposure_short": 0.0,
        "adg_weighted_per_exposure_long": 0.0013139757156326315,
        "adg_weighted_per_exposure_short": 0.0,
        "drawdown_1pct_worst_mean_long": 0.23178863745365294,
        "drawdown_1pct_worst_mean_short": -0.0,
        "drawdown_max_long": 0.26381396906755217,
        "drawdown_max_short": -0.0,
        "exposure_ratios_mean_long": 0.13147956666659752,
        "exposure_ratios_mean_short": 0.0,
        "hrs_stuck_max_long": 102.15,
        "hrs_stuck_max_short": NaN,
        "loss_profit_ratio_long": 0.2631038410996929,
        "loss_profit_ratio_short": 1.0,
        "n_days": 472.9583333333333,
        "pa_distance_1pct_worst_mean_long": 0.286813571223721,
        "pa_distance_1pct_worst_mean_short": 100.0,
        "pa_distance_max_long": 0.24903568687620461,
        "pa_distance_max_short": 100.0,
        "pa_distance_mean_long": 0.02949965999332736,
        "pa_distance_mean_short": 100.0,
        "pa_distance_std_long": 0.0389333436628694,
        "pa_distance_std_short": 1.0,
        "sharpe_ratio_long": 0.0874929751262277,
        "sharpe_ratio_short": 0.0,
        "starting_balance": 10000.0,
        "time_at_max_exposure_long": 0.06528137497227902,
        "time_at_max_exposure_short": 0.0,
        "timestamp_finished": 1714163062343.039
    },
    "CELOUSDT": {
        "adg_per_exposure_long": 0.000908840885507356,
        "adg_per_exposure_short": 0.0,
        "adg_weighted_per_exposure_long": 0.000908840885507356,
        "adg_weighted_per_exposure_short": 0.0,
        "drawdown_1pct_worst_mean_long": 0.2189403627155614,
        "drawdown_1pct_worst_mean_short": -0.0,
        "drawdown_max_long": 0.29057554087710136,
        "drawdown_max_short": -0.0,
        "exposure_ratios_mean_long": 0.11840291975742945,
        "exposure_ratios_mean_short": 0.0,
        "hrs_stuck_max_long": 159.55,
        "hrs_stuck_max_short": NaN,
        "loss_profit_ratio_long": 0.145768876612053,
        "loss_profit_ratio_short": 1.0,
        "n_days": 472.9583333333333,
        "pa_distance_1pct_worst_mean_long": 0.25900193610406164,
        "pa_distance_1pct_worst_mean_short": 100.0,
        "pa_distance_max_long": 0.22590174787762898,
        "pa_distance_max_short": 100.0,
        "pa_distance_mean_long": 0.02314911581141286,
        "pa_distance_mean_short": 100.0,
        "pa_distance_std_long": 0.02756346970417579,
        "pa_distance_std_short": 1.0,
        "sharpe_ratio_long": 0.06842221881070401,
        "sharpe_ratio_short": 0.0,
        "starting_balance": 10000.0,
        "time_at_max_exposure_long": 0.05826968956709357,
        "time_at_max_exposure_short": 0.0,
        "timestamp_finished": 1714163062343.041
    },
    "DYDXUSDT": {
        "adg_per_exposure_long": 0.0011327643030643042,
        "adg_per_exposure_short": 0.0,
        "adg_weighted_per_exposure_long": 0.0011327643030643042,
        "adg_weighted_per_exposure_short": 0.0,
        "drawdown_1pct_worst_mean_long": 0.17623189770013742,
        "drawdown_1pct_worst_mean_short": -0.0,
        "drawdown_max_long": 0.30165466193480445,
        "drawdown_max_short": -0.0,
        "exposure_ratios_mean_long": 0.06115912743492591,
        "exposure_ratios_mean_short": 0.0,
        "hrs_stuck_max_long": 176.46666666666667,
        "hrs_stuck_max_short": NaN,
        "loss_profit_ratio_long": 0.040024534152548086,
        "loss_profit_ratio_short": 1.0,
        "n_days": 472.9583333333333,
        "pa_distance_1pct_worst_mean_long": 0.19744343107533935,
        "pa_distance_1pct_worst_mean_short": 100.0,
        "pa_distance_max_long": 0.21469507094752957,
        "pa_distance_max_short": 100.0,
        "pa_distance_mean_long": 0.017199471245322437,
        "pa_distance_mean_short": 100.0,
        "pa_distance_std_long": 0.020675008012640533,
        "pa_distance_std_short": 1.0,
        "sharpe_ratio_long": 0.07487532475199485,
        "sharpe_ratio_short": 0.0,
        "starting_balance": 10000.0,
        "time_at_max_exposure_long": 0.00986578086835176,
        "time_at_max_exposure_short": 0.0,
        "timestamp_finished": 1714163062343.0222
    },
    "FILUSDT": {
        "adg_per_exposure_long": 0.0007552459642632403,
        "adg_per_exposure_short": 0.0,
        "adg_weighted_per_exposure_long": 0.0007552459642632403,
        "adg_weighted_per_exposure_short": 0.0,
        "drawdown_1pct_worst_mean_long": 0.1912824457278484,
        "drawdown_1pct_worst_mean_short": -0.0,
        "drawdown_max_long": 0.28364909346448686,
        "drawdown_max_short": -0.0,
        "exposure_ratios_mean_long": 0.16932311311253823,
        "exposure_ratios_mean_short": 0.0,
        "hrs_stuck_max_long": 240.66666666666666,
        "hrs_stuck_max_short": NaN,
        "loss_profit_ratio_long": 0.25327011653661213,
        "loss_profit_ratio_short": 1.0,
        "n_days": 472.9583333333333,
        "pa_distance_1pct_worst_mean_long": 0.21310917934349102,
        "pa_distance_1pct_worst_mean_short": 100.0,
        "pa_distance_max_long": 0.252197575943541,
        "pa_distance_max_short": 100.0,
        "pa_distance_mean_long": 0.022949641071897158,
        "pa_distance_mean_short": 100.0,
        "pa_distance_std_long": 0.030628276785933085,
        "pa_distance_std_short": 1.0,
        "sharpe_ratio_long": 0.035127410895130974,
        "sharpe_ratio_short": 0.0,
        "starting_balance": 10000.0,
        "time_at_max_exposure_long": 0.08313652418129455,
        "time_at_max_exposure_short": 0.0,
        "timestamp_finished": 1714163062343.044
    },
    "FTMUSDT": {
        "adg_per_exposure_long": 0.0010768180758997659,
        "adg_per_exposure_short": 0.0,
        "adg_weighted_per_exposure_long": 0.0010768180758997659,
        "adg_weighted_per_exposure_short": 0.0,
        "drawdown_1pct_worst_mean_long": 0.13894235514043624,
        "drawdown_1pct_worst_mean_short": -0.0,
        "drawdown_max_long": 0.23823221839555447,
        "drawdown_max_short": -0.0,
        "exposure_ratios_mean_long": 0.08678426282861038,
        "exposure_ratios_mean_short": 0.0,
        "hrs_stuck_max_long": 203.88333333333333,
        "hrs_stuck_max_short": NaN,
        "loss_profit_ratio_long": 0.03357486248914536,
        "loss_profit_ratio_short": 1.0,
        "n_days": 472.9583333333333,
        "pa_distance_1pct_worst_mean_long": 0.15041216959243653,
        "pa_distance_1pct_worst_mean_short": 100.0,
        "pa_distance_max_long": 0.17640991927673844,
        "pa_distance_max_short": 100.0,
        "pa_distance_mean_long": 0.016923874515195208,
        "pa_distance_mean_short": 100.0,
        "pa_distance_std_long": 0.018707412717250304,
        "pa_distance_std_short": 1.0,
        "sharpe_ratio_long": 0.0826024037099408,
        "sharpe_ratio_short": 0.0,
        "starting_balance": 10000.0,
        "time_at_max_exposure_long": 0.016005452785590343,
        "time_at_max_exposure_short": 0.0,
        "timestamp_finished": 1714163062343.035
    },
    "GALAUSDT": {
        "adg_per_exposure_long": 0.0011721002867153274,
        "adg_per_exposure_short": 0.0,
        "adg_weighted_per_exposure_long": 0.0011721002867153274,
        "adg_weighted_per_exposure_short": 0.0,
        "drawdown_1pct_worst_mean_long": 0.1840175211444381,
        "drawdown_1pct_worst_mean_short": -0.0,
        "drawdown_max_long": 0.20253543258308923,
        "drawdown_max_short": -0.0,
        "exposure_ratios_mean_long": 0.1241372504769166,
        "exposure_ratios_mean_short": 0.0,
        "hrs_stuck_max_long": 194.11666666666667,
        "hrs_stuck_max_short": NaN,
        "loss_profit_ratio_long": 0.20705677108214574,
        "loss_profit_ratio_short": 1.0,
        "n_days": 472.9583333333333,
        "pa_distance_1pct_worst_mean_long": 0.16511554817756352,
        "pa_distance_1pct_worst_mean_short": 100.0,
        "pa_distance_max_long": 0.1865312627990059,
        "pa_distance_max_short": 100.0,
        "pa_distance_mean_long": 0.02329414493855043,
        "pa_distance_mean_short": 100.0,
        "pa_distance_std_long": 0.02823887437565977,
        "pa_distance_std_short": 1.0,
        "sharpe_ratio_long": 0.10028124338038494,
        "sharpe_ratio_short": 0.0,
        "starting_balance": 10000.0,
        "time_at_max_exposure_long": 0.07302412953842052,
        "time_at_max_exposure_short": 0.0,
        "timestamp_finished": 1714163062343.0469
    },
    "GMTUSDT": {
        "adg_per_exposure_long": 0.0005565063723667052,
        "adg_per_exposure_short": 0.0,
        "adg_weighted_per_exposure_long": 0.0005565063723667052,
        "adg_weighted_per_exposure_short": 0.0,
        "drawdown_1pct_worst_mean_long": 0.3425519705129103,
        "drawdown_1pct_worst_mean_short": -0.0,
        "drawdown_max_long": 0.3524909498758294,
        "drawdown_max_short": -0.0,
        "exposure_ratios_mean_long": 0.2822893537676743,
        "exposure_ratios_mean_short": 0.0,
        "hrs_stuck_max_long": 274.9,
        "hrs_stuck_max_short": NaN,
        "loss_profit_ratio_long": 0.9715674231261971,
        "loss_profit_ratio_short": 1.0,
        "n_days": 472.9583333333333,
        "pa_distance_1pct_worst_mean_long": 0.26620618920818295,
        "pa_distance_1pct_worst_mean_short": 100.0,
        "pa_distance_max_long": 0.2600185552363696,
        "pa_distance_max_short": 100.0,
        "pa_distance_mean_long": 0.046909535529204,
        "pa_distance_mean_short": 100.0,
        "pa_distance_std_long": 0.04836120180880533,
        "pa_distance_std_short": 1.0,
        "sharpe_ratio_long": 0.04219481983444758,
        "sharpe_ratio_short": 0.0,
        "starting_balance": 10000.0,
        "time_at_max_exposure_long": 0.20639673391551625,
        "time_at_max_exposure_short": 0.0,
        "timestamp_finished": 1714163062343.064
    },
    "GRTUSDT": {
        "adg_per_exposure_long": 0.001072598217904952,
        "adg_per_exposure_short": 0.0,
        "adg_weighted_per_exposure_long": 0.001072598217904952,
        "adg_weighted_per_exposure_short": 0.0,
        "drawdown_1pct_worst_mean_long": 0.0745155080026066,
        "drawdown_1pct_worst_mean_short": -0.0,
        "drawdown_max_long": 0.23882534547000062,
        "drawdown_max_short": -0.0,
        "exposure_ratios_mean_long": 0.05600654528684092,
        "exposure_ratios_mean_short": 0.0,
        "hrs_stuck_max_long": 203.13333333333333,
        "hrs_stuck_max_short": NaN,
        "loss_profit_ratio_long": 0.011568938263446545,
        "loss_profit_ratio_short": 1.0,
        "n_days": 472.9583333333333,
        "pa_distance_1pct_worst_mean_long": 0.09078194516259912,
        "pa_distance_1pct_worst_mean_short": 100.0,
        "pa_distance_max_long": 0.16911946290882512,
        "pa_distance_max_short": 100.0,
        "pa_distance_mean_long": 0.015172986687549411,
        "pa_distance_mean_short": 100.0,
        "pa_distance_std_long": 0.014416488445356274,
        "pa_distance_std_short": 1.0,
        "sharpe_ratio_long": 0.10939007881447874,
        "sharpe_ratio_short": 0.0,
        "starting_balance": 10000.0,
        "time_at_max_exposure_long": 0.005012171618108227,
        "time_at_max_exposure_short": 0.0,
        "timestamp_finished": 1714163062343.036
    },
    "IMXUSDT": {
        "adg_per_exposure_long": 0.0008522613267030188,
        "adg_per_exposure_short": 0.0,
        "adg_weighted_per_exposure_long": 0.0008522613267030188,
        "adg_weighted_per_exposure_short": 0.0,
        "drawdown_1pct_worst_mean_long": 0.20816111571227383,
        "drawdown_1pct_worst_mean_short": -0.0,
        "drawdown_max_long": 0.22797374708230564,
        "drawdown_max_short": -0.0,
        "exposure_ratios_mean_long": 0.19074018033566487,
        "exposure_ratios_mean_short": 0.0,
        "hrs_stuck_max_long": 129.15,
        "hrs_stuck_max_short": NaN,
        "loss_profit_ratio_long": 0.4260942886886479,
        "loss_profit_ratio_short": 1.0,
        "n_days": 472.9583333333333,
        "pa_distance_1pct_worst_mean_long": 0.18228516482813203,
        "pa_distance_1pct_worst_mean_short": 100.0,
        "pa_distance_max_long": 0.18264416499575759,
        "pa_distance_max_short": 100.0,
        "pa_distance_mean_long": 0.030491720812235768,
        "pa_distance_mean_short": 100.0,
        "pa_distance_std_long": 0.033075839986804724,
        "pa_distance_std_short": 1.0,
        "sharpe_ratio_long": 0.0731353479811933,
        "sharpe_ratio_short": 0.0,
        "starting_balance": 10000.0,
        "time_at_max_exposure_long": 0.15026756453882945,
        "time_at_max_exposure_short": 0.0,
        "timestamp_finished": 1714163062343.065
    },
    "INJUSDT": {
        "adg_per_exposure_long": 0.0012337321836966009,
        "adg_per_exposure_short": 0.0,
        "adg_weighted_per_exposure_long": 0.0012337321836966009,
        "adg_weighted_per_exposure_short": 0.0,
        "drawdown_1pct_worst_mean_long": 0.10577204526533174,
        "drawdown_1pct_worst_mean_short": -0.0,
        "drawdown_max_long": 0.2607180910232566,
        "drawdown_max_short": -0.0,
        "exposure_ratios_mean_long": 0.039586443609220305,
        "exposure_ratios_mean_short": 0.0,
        "hrs_stuck_max_long": 122.78333333333333,
        "hrs_stuck_max_short": NaN,
        "loss_profit_ratio_long": 0.01915933335774219,
        "loss_profit_ratio_short": 1.0,
        "n_days": 472.9583333333333,
        "pa_distance_1pct_worst_mean_long": 0.11387349946118837,
        "pa_distance_1pct_worst_mean_short": 100.0,
        "pa_distance_max_long": 0.1808212001841464,
        "pa_distance_max_short": 100.0,
        "pa_distance_mean_long": 0.016038438669570186,
        "pa_distance_mean_short": 100.0,
        "pa_distance_std_long": 0.01580922454962019,
        "pa_distance_std_short": 1.0,
        "sharpe_ratio_long": 0.11652668331854805,
        "sharpe_ratio_short": 0.0,
        "starting_balance": 10000.0,
        "time_at_max_exposure_long": 0.007399344380748948,
        "time_at_max_exposure_short": 0.0,
        "timestamp_finished": 1714163062343.032
    },
    "JASMYUSDT": {
        "adg_per_exposure_long": 0.0012403148669599684,
        "adg_per_exposure_short": 0.0,
        "adg_weighted_per_exposure_long": 0.0012403148669599684,
        "adg_weighted_per_exposure_short": 0.0,
        "drawdown_1pct_worst_mean_long": 0.024557797748750027,
        "drawdown_1pct_worst_mean_short": -0.0,
        "drawdown_max_long": 0.08647191154463561,
        "drawdown_max_short": -0.0,
        "exposure_ratios_mean_long": 0.03295428023892731,
        "exposure_ratios_mean_short": 0.0,
        "hrs_stuck_max_long": 162.63333333333333,
        "hrs_stuck_max_short": NaN,
        "loss_profit_ratio_long": 0.0,
        "loss_profit_ratio_short": 1.0,
        "n_days": 472.9583333333333,
        "pa_distance_1pct_worst_mean_long": 0.04751171705716541,
        "pa_distance_1pct_worst_mean_short": 100.0,
        "pa_distance_max_long": 0.07035826850217326,
        "pa_distance_max_short": 100.0,
        "pa_distance_mean_long": 0.013134138143160879,
        "pa_distance_mean_short": 100.0,
        "pa_distance_std_long": 0.009908871186986067,
        "pa_distance_std_short": 1.0,
        "sharpe_ratio_long": 0.22436332061704545,
        "sharpe_ratio_short": 0.0,
        "starting_balance": 10000.0,
        "time_at_max_exposure_long": 0.00018498360951872372,
        "time_at_max_exposure_short": 0.0,
        "timestamp_finished": 1714163062343.038
    },
    "LDOUSDT": {
        "adg_per_exposure_long": 0.0010091398761526982,
        "adg_per_exposure_short": 0.0,
        "adg_weighted_per_exposure_long": 0.0010091398761526982,
        "adg_weighted_per_exposure_short": 0.0,
        "drawdown_1pct_worst_mean_long": 0.1676295186680915,
        "drawdown_1pct_worst_mean_short": -0.0,
        "drawdown_max_long": 0.2930453741558896,
        "drawdown_max_short": -0.0,
        "exposure_ratios_mean_long": 0.08468773263790405,
        "exposure_ratios_mean_short": 0.0,
        "hrs_stuck_max_long": 153.71666666666667,
        "hrs_stuck_max_short": NaN,
        "loss_profit_ratio_long": 0.0839395980278573,
        "loss_profit_ratio_short": 1.0,
        "n_days": 472.9583333333333,
        "pa_distance_1pct_worst_mean_long": 0.18654749857146122,
        "pa_distance_1pct_worst_mean_short": 100.0,
        "pa_distance_max_long": 0.24986033630189325,
        "pa_distance_max_short": 100.0,
        "pa_distance_mean_long": 0.02078502529257207,
        "pa_distance_mean_short": 100.0,
        "pa_distance_std_long": 0.023967842630312694,
        "pa_distance_std_short": 1.0,
        "sharpe_ratio_long": 0.04677892886568691,
        "sharpe_ratio_short": 0.0,
        "starting_balance": 10000.0,
        "time_at_max_exposure_long": 0.037666071664960346,
        "time_at_max_exposure_short": 0.0,
        "timestamp_finished": 1714163062343.042
    },
    "LINAUSDT": {
        "adg_per_exposure_long": 0.0004753812842830385,
        "adg_per_exposure_short": 0.0,
        "adg_weighted_per_exposure_long": 0.0004753812842830385,
        "adg_weighted_per_exposure_short": 0.0,
        "drawdown_1pct_worst_mean_long": 0.4136606009831287,
        "drawdown_1pct_worst_mean_short": -0.0,
        "drawdown_max_long": 0.5213907554128785,
        "drawdown_max_short": -0.0,
        "exposure_ratios_mean_long": 0.18460027337527857,
        "exposure_ratios_mean_short": 0.0,
        "hrs_stuck_max_long": 163.46666666666667,
        "hrs_stuck_max_short": NaN,
        "loss_profit_ratio_long": 0.5826571649356193,
        "loss_profit_ratio_short": 1.0,
        "n_days": 472.9583333333333,
        "pa_distance_1pct_worst_mean_long": 0.6394287673857064,
        "pa_distance_1pct_worst_mean_short": 100.0,
        "pa_distance_max_long": 0.7464142336551269,
        "pa_distance_max_short": 100.0,
        "pa_distance_mean_long": 0.05459482990364948,
        "pa_distance_mean_short": 100.0,
        "pa_distance_std_long": 0.10641308430869523,
        "pa_distance_std_short": 1.0,
        "sharpe_ratio_long": 0.006865727569139359,
        "sharpe_ratio_short": 0.0,
        "starting_balance": 10000.0,
        "time_at_max_exposure_long": 0.14457731755414882,
        "time_at_max_exposure_short": 0.0,
        "timestamp_finished": 1714163062343.062
    },
    "LUNA2USDT": {
        "adg_per_exposure_long": 0.0011770408552664868,
        "adg_per_exposure_short": 0.0,
        "adg_weighted_per_exposure_long": 0.0011770408552664868,
        "adg_weighted_per_exposure_short": 0.0,
        "drawdown_1pct_worst_mean_long": 0.2468661483665855,
        "drawdown_1pct_worst_mean_short": -0.0,
        "drawdown_max_long": 0.34887012723893485,
        "drawdown_max_short": -0.0,
        "exposure_ratios_mean_long": 0.11748087429001108,
        "exposure_ratios_mean_short": 0.0,
        "hrs_stuck_max_long": 162.81666666666666,
        "hrs_stuck_max_short": NaN,
        "loss_profit_ratio_long": 0.19166454610598277,
        "loss_profit_ratio_short": 1.0,
        "n_days": 472.9583333333333,
        "pa_distance_1pct_worst_mean_long": 0.2924747464831046,
        "pa_distance_1pct_worst_mean_short": 100.0,
        "pa_distance_max_long": 0.2929250680180656,
        "pa_distance_max_short": 100.0,
        "pa_distance_mean_long": 0.024602408635330288,
        "pa_distance_mean_short": 100.0,
        "pa_distance_std_long": 0.03807523235395983,
        "pa_distance_std_short": 1.0,
        "sharpe_ratio_long": 0.04961045675727243,
        "sharpe_ratio_short": 0.0,
        "starting_balance": 10000.0,
        "time_at_max_exposure_long": 0.08292511545035065,
        "time_at_max_exposure_short": 0.0,
        "timestamp_finished": 1714163062343.066
    },
    "MASKUSDT": {
        "adg_per_exposure_long": 0.0010765324456543102,
        "adg_per_exposure_short": 0.0,
        "adg_weighted_per_exposure_long": 0.0010765324456543102,
        "adg_weighted_per_exposure_short": 0.0,
        "drawdown_1pct_worst_mean_long": 0.20079793971939164,
        "drawdown_1pct_worst_mean_short": -0.0,
        "drawdown_max_long": 0.269840948748512,
        "drawdown_max_short": -0.0,
        "exposure_ratios_mean_long": 0.05121254170327906,
        "exposure_ratios_mean_short": 0.0,
        "hrs_stuck_max_long": 150.58333333333334,
        "hrs_stuck_max_short": NaN,
        "loss_profit_ratio_long": 0.058492255696543684,
        "loss_profit_ratio_short": 1.0,
        "n_days": 472.9583333333333,
        "pa_distance_1pct_worst_mean_long": 0.23105261524300644,
        "pa_distance_1pct_worst_mean_short": 100.0,
        "pa_distance_max_long": 0.20775390723105644,
        "pa_distance_max_short": 100.0,
        "pa_distance_mean_long": 0.016266662141369327,
        "pa_distance_mean_short": 100.0,
        "pa_distance_std_long": 0.02347231366402424,
        "pa_distance_std_short": 1.0,
        "sharpe_ratio_long": 0.05692463520024893,
        "sharpe_ratio_short": 0.0,
        "starting_balance": 10000.0,
        "time_at_max_exposure_long": 0.014173261889675137,
        "time_at_max_exposure_short": 0.0,
        "timestamp_finished": 1714163062343.051
    },
    "MTLUSDT": {
        "adg_per_exposure_long": 0.001090988323265929,
        "adg_per_exposure_short": 0.0,
        "adg_weighted_per_exposure_long": 0.001090988323265929,
        "adg_weighted_per_exposure_short": 0.0,
        "drawdown_1pct_worst_mean_long": 0.22030598136677954,
        "drawdown_1pct_worst_mean_short": -0.0,
        "drawdown_max_long": 0.2854385184097945,
        "drawdown_max_short": -0.0,
        "exposure_ratios_mean_long": 0.06672651700306279,
        "exposure_ratios_mean_short": 0.0,
        "hrs_stuck_max_long": 194.86666666666667,
        "hrs_stuck_max_short": NaN,
        "loss_profit_ratio_long": 0.14068649676049344,
        "loss_profit_ratio_short": 1.0,
        "n_days": 472.9583333333333,
        "pa_distance_1pct_worst_mean_long": 0.2556570097712809,
        "pa_distance_1pct_worst_mean_short": 100.0,
        "pa_distance_max_long": 0.26196893154972206,
        "pa_distance_max_short": 100.0,
        "pa_distance_mean_long": 0.02141962538217751,
        "pa_distance_mean_short": 100.0,
        "pa_distance_std_long": 0.03377031577602831,
        "pa_distance_std_short": 1.0,
        "sharpe_ratio_long": 0.09660851488177102,
        "sharpe_ratio_short": 0.0,
        "starting_balance": 10000.0,
        "time_at_max_exposure_long": 0.030143366080153906,
        "time_at_max_exposure_short": 0.0,
        "timestamp_finished": 1714163062343.055
    },
    "NEARUSDT": {
        "adg_per_exposure_long": 0.0010023379190302606,
        "adg_per_exposure_short": 0.0,
        "adg_weighted_per_exposure_long": 0.0010023379190302606,
        "adg_weighted_per_exposure_short": 0.0,
        "drawdown_1pct_worst_mean_long": 0.09673473975764452,
        "drawdown_1pct_worst_mean_short": -0.0,
        "drawdown_max_long": 0.14384325921827265,
        "drawdown_max_short": -0.0,
        "exposure_ratios_mean_long": 0.08907546883561057,
        "exposure_ratios_mean_short": 0.0,
        "hrs_stuck_max_long": 285.0,
        "hrs_stuck_max_short": NaN,
        "loss_profit_ratio_long": 0.07381150518208196,
        "loss_profit_ratio_short": 1.0,
        "n_days": 472.9583333333333,
        "pa_distance_1pct_worst_mean_long": 0.09688636598025349,
        "pa_distance_1pct_worst_mean_short": 100.0,
        "pa_distance_max_long": 0.12934712375615703,
        "pa_distance_max_short": 100.0,
        "pa_distance_mean_long": 0.017396581930446776,
        "pa_distance_mean_short": 100.0,
        "pa_distance_std_long": 0.016796879862398105,
        "pa_distance_std_short": 1.0,
        "sharpe_ratio_long": 0.1256098141643996,
        "sharpe_ratio_short": 0.0,
        "starting_balance": 10000.0,
        "time_at_max_exposure_long": 0.03633592315818339,
        "time_at_max_exposure_short": 0.0,
        "timestamp_finished": 1714163062343.059
    },
    "OCEANUSDT": {
        "adg_per_exposure_long": 0.0010667019767929276,
        "adg_per_exposure_short": 0.0,
        "adg_weighted_per_exposure_long": 0.0010667019767929276,
        "adg_weighted_per_exposure_short": 0.0,
        "drawdown_1pct_worst_mean_long": 0.08096020788830044,
        "drawdown_1pct_worst_mean_short": -0.0,
        "drawdown_max_long": 0.18261082838684922,
        "drawdown_max_short": -0.0,
        "exposure_ratios_mean_long": 0.08431393425716546,
        "exposure_ratios_mean_short": 0.0,
        "hrs_stuck_max_long": 195.41666666666666,
        "hrs_stuck_max_short": NaN,
        "loss_profit_ratio_long": 0.0269403410500557,
        "loss_profit_ratio_short": 1.0,
        "n_days": 472.9583333333333,
        "pa_distance_1pct_worst_mean_long": 0.08293560734905735,
        "pa_distance_1pct_worst_mean_short": 100.0,
        "pa_distance_max_long": 0.17662154110618183,
        "pa_distance_max_short": 100.0,
        "pa_distance_mean_long": 0.01635702155398681,
        "pa_distance_mean_short": 100.0,
        "pa_distance_std_long": 0.014549572774179193,
        "pa_distance_std_short": 1.0,
        "sharpe_ratio_long": 0.10245819458511662,
        "sharpe_ratio_short": 0.0,
        "starting_balance": 10000.0,
        "time_at_max_exposure_long": 0.03851165227193968,
        "time_at_max_exposure_short": 0.0,
        "timestamp_finished": 1714163062343.05
    },
    "OPUSDT": {
        "adg_per_exposure_long": 0.0010643526749138932,
        "adg_per_exposure_short": 0.0,
        "adg_weighted_per_exposure_long": 0.0010643526749138932,
        "adg_weighted_per_exposure_short": 0.0,
        "drawdown_1pct_worst_mean_long": 0.16064265586822174,
        "drawdown_1pct_worst_mean_short": -0.0,
        "drawdown_max_long": 0.26214611225624085,
        "drawdown_max_short": -0.0,
        "exposure_ratios_mean_long": 0.07570413075482027,
        "exposure_ratios_mean_short": 0.0,
        "hrs_stuck_max_long": 173.6,
        "hrs_stuck_max_short": NaN,
        "loss_profit_ratio_long": 0.05208149905261147,
        "loss_profit_ratio_short": 1.0,
        "n_days": 472.9583333333333,
        "pa_distance_1pct_worst_mean_long": 0.17589935918414615,
        "pa_distance_1pct_worst_mean_short": 100.0,
        "pa_distance_max_long": 0.23034626185706078,
        "pa_distance_max_short": 100.0,
        "pa_distance_mean_long": 0.017803645855155356,
        "pa_distance_mean_short": 100.0,
        "pa_distance_std_long": 0.020956121313352814,
        "pa_distance_std_short": 1.0,
        "sharpe_ratio_long": 0.06194265760884647,
        "sharpe_ratio_short": 0.0,
        "starting_balance": 10000.0,
        "time_at_max_exposure_long": 0.01978438482115574,
        "time_at_max_exposure_short": 0.0,
        "timestamp_finished": 1714163062343.045
    },
    "PEOPLEUSDT": {
        "adg_per_exposure_long": 0.001101438324823345,
        "adg_per_exposure_short": 0.0,
        "adg_weighted_per_exposure_long": 0.001101438324823345,
        "adg_weighted_per_exposure_short": 0.0,
        "drawdown_1pct_worst_mean_long": 0.18582094636154878,
        "drawdown_1pct_worst_mean_short": -0.0,
        "drawdown_max_long": 0.2966996123409561,
        "drawdown_max_short": -0.0,
        "exposure_ratios_mean_long": 0.13968725267230162,
        "exposure_ratios_mean_short": 0.0,
        "hrs_stuck_max_long": 184.31666666666666,
        "hrs_stuck_max_short": NaN,
        "loss_profit_ratio_long": 0.20716612786197713,
        "loss_profit_ratio_short": 1.0,
        "n_days": 472.9583333333333,
        "pa_distance_1pct_worst_mean_long": 0.2118977438088735,
        "pa_distance_1pct_worst_mean_short": 100.0,
        "pa_distance_max_long": 0.2759092133793514,
        "pa_distance_max_short": 100.0,
        "pa_distance_mean_long": 0.024055835422824683,
        "pa_distance_mean_short": 100.0,
        "pa_distance_std_long": 0.033862814378948315,
        "pa_distance_std_short": 1.0,
        "sharpe_ratio_long": 0.05126362760272836,
        "sharpe_ratio_short": 0.0,
        "starting_balance": 10000.0,
        "time_at_max_exposure_long": 0.08947000230768788,
        "time_at_max_exposure_short": 0.0,
        "timestamp_finished": 1714163062343.0679
    },
    "SNXUSDT": {
        "adg_per_exposure_long": 0.0011378176949210506,
        "adg_per_exposure_short": 0.0,
        "adg_weighted_per_exposure_long": 0.0011378176949210506,
        "adg_weighted_per_exposure_short": 0.0,
        "drawdown_1pct_worst_mean_long": 0.10690390612764629,
        "drawdown_1pct_worst_mean_short": -0.0,
        "drawdown_max_long": 0.21433666933333606,
        "drawdown_max_short": -0.0,
        "exposure_ratios_mean_long": 0.06601628651433958,
        "exposure_ratios_mean_short": 0.0,
        "hrs_stuck_max_long": 171.91666666666666,
        "hrs_stuck_max_short": NaN,
        "loss_profit_ratio_long": 0.02013756138654938,
        "loss_profit_ratio_short": 1.0,
        "n_days": 472.9583333333333,
        "pa_distance_1pct_worst_mean_long": 0.12423885251477482,
        "pa_distance_1pct_worst_mean_short": 100.0,
        "pa_distance_max_long": 0.15298140523047812,
        "pa_distance_max_short": 100.0,
        "pa_distance_mean_long": 0.016538563236577212,
        "pa_distance_mean_short": 100.0,
        "pa_distance_std_long": 0.016388712590695152,
        "pa_distance_std_short": 1.0,
        "sharpe_ratio_long": 0.11450108483883847,
        "sharpe_ratio_short": 0.0,
        "starting_balance": 10000.0,
        "time_at_max_exposure_long": 0.010438330338925945,
        "time_at_max_exposure_short": 0.0,
        "timestamp_finished": 1714163062343.048
    },
    "SOLUSDT": {
        "adg_per_exposure_long": 0.000892051582375375,
        "adg_per_exposure_short": 0.0,
        "adg_weighted_per_exposure_long": 0.000892051582375375,
        "adg_weighted_per_exposure_short": 0.0,
        "drawdown_1pct_worst_mean_long": 0.07930763447764025,
        "drawdown_1pct_worst_mean_short": -0.0,
        "drawdown_max_long": 0.1337695443635043,
        "drawdown_max_short": -0.0,
        "exposure_ratios_mean_long": 0.04947243272230637,
        "exposure_ratios_mean_short": 0.0,
        "hrs_stuck_max_long": 171.45,
        "hrs_stuck_max_short": NaN,
        "loss_profit_ratio_long": 0.04425258198356885,
        "loss_profit_ratio_short": 1.0,
        "n_days": 472.9583333333333,
        "pa_distance_1pct_worst_mean_long": 0.0813664218472417,
        "pa_distance_1pct_worst_mean_short": 100.0,
        "pa_distance_max_long": 0.1249389574689574,
        "pa_distance_max_short": 100.0,
        "pa_distance_mean_long": 0.014304789942893869,
        "pa_distance_mean_short": 100.0,
        "pa_distance_std_long": 0.013273876068628232,
        "pa_distance_std_short": 1.0,
        "sharpe_ratio_long": 0.17299623549057655,
        "sharpe_ratio_short": 0.0,
        "starting_balance": 10000.0,
        "time_at_max_exposure_long": 0.017908080927060456,
        "time_at_max_exposure_short": 0.0,
        "timestamp_finished": 1714163062343.0532
    },
    "STMXUSDT": {
        "adg_per_exposure_long": 0.0007499638647592288,
        "adg_per_exposure_short": 0.0,
        "adg_weighted_per_exposure_long": 0.0007499638647592288,
        "adg_weighted_per_exposure_short": 0.0,
        "drawdown_1pct_worst_mean_long": 0.24047567523038932,
        "drawdown_1pct_worst_mean_short": -0.0,
        "drawdown_max_long": 0.26995938766466643,
        "drawdown_max_short": -0.0,
        "exposure_ratios_mean_long": 0.20199498737543423,
        "exposure_ratios_mean_short": 0.0,
        "hrs_stuck_max_long": 282.4,
        "hrs_stuck_max_short": NaN,
        "loss_profit_ratio_long": 0.44961857927140125,
        "loss_profit_ratio_short": 1.0,
        "n_days": 472.9583333333333,
        "pa_distance_1pct_worst_mean_long": 0.2449851417521056,
        "pa_distance_1pct_worst_mean_short": 100.0,
        "pa_distance_max_long": 0.244582015660268,
        "pa_distance_max_short": 100.0,
        "pa_distance_mean_long": 0.03426720958612693,
        "pa_distance_mean_short": 100.0,
        "pa_distance_std_long": 0.041689057197206524,
        "pa_distance_std_short": 1.0,
        "sharpe_ratio_long": 0.05477075377928205,
        "sharpe_ratio_short": 0.0,
        "starting_balance": 10000.0,
        "time_at_max_exposure_long": 0.10231304197493388,
        "time_at_max_exposure_short": 0.0,
        "timestamp_finished": 1714163062343.069
    },
    "STORJUSDT": {
        "adg_per_exposure_long": -0.0003934528875922938,
        "adg_per_exposure_short": 0.0,
        "adg_weighted_per_exposure_long": -0.0003934528875922938,
        "adg_weighted_per_exposure_short": 0.0,
        "drawdown_1pct_worst_mean_long": 0.5001757776307257,
        "drawdown_1pct_worst_mean_short": -0.0,
        "drawdown_max_long": 0.5386518715568478,
        "drawdown_max_short": -0.0,
        "exposure_ratios_mean_long": 0.2544722067524046,
        "exposure_ratios_mean_short": 0.0,
        "hrs_stuck_max_long": 314.25,
        "hrs_stuck_max_short": NaN,
        "loss_profit_ratio_long": 1.3140804816390146,
        "loss_profit_ratio_short": 1.0,
        "n_days": 472.9583333333333,
        "pa_distance_1pct_worst_mean_long": 0.4128778748538803,
        "pa_distance_1pct_worst_mean_short": 100.0,
        "pa_distance_max_long": 0.47343624466248846,
        "pa_distance_max_short": 100.0,
        "pa_distance_mean_long": 0.06695229341321274,
        "pa_distance_mean_short": 100.0,
        "pa_distance_std_long": 0.08957780085753776,
        "pa_distance_std_short": 1.0,
        "sharpe_ratio_long": -0.007279693689667101,
        "sharpe_ratio_short": 0.0,
        "starting_balance": 10000.0,
        "time_at_max_exposure_long": 0.2075423527460012,
        "time_at_max_exposure_short": 0.0,
        "timestamp_finished": 1714163062343.073
    },
    "TRBUSDT": {
        "adg_per_exposure_long": -0.00011889164805478636,
        "adg_per_exposure_short": 0.0,
        "adg_weighted_per_exposure_long": -0.00011889164805478636,
        "adg_weighted_per_exposure_short": 0.0,
        "drawdown_1pct_worst_mean_long": 0.5692280109212362,
        "drawdown_1pct_worst_mean_short": -0.0,
        "drawdown_max_long": 0.5915714327937568,
        "drawdown_max_short": -0.0,
        "exposure_ratios_mean_long": 0.15876901952875988,
        "exposure_ratios_mean_short": 0.0,
        "hrs_stuck_max_long": 143.26666666666668,
        "hrs_stuck_max_short": NaN,
        "loss_profit_ratio_long": 0.7326007157457933,
        "loss_profit_ratio_short": 1.0,
        "n_days": 472.9583333333333,
        "pa_distance_1pct_worst_mean_long": 0.8558754103479659,
        "pa_distance_1pct_worst_mean_short": 100.0,
        "pa_distance_max_long": 0.7404736753832769,
        "pa_distance_max_short": 100.0,
        "pa_distance_mean_long": 0.08293558970817355,
        "pa_distance_mean_short": 100.0,
        "pa_distance_std_long": 0.14008864140499017,
        "pa_distance_std_short": 1.0,
        "sharpe_ratio_long": -0.00449303276221858,
        "sharpe_ratio_short": 0.0,
        "starting_balance": 10000.0,
        "time_at_max_exposure_long": 0.11895296149916841,
        "time_at_max_exposure_short": 0.0,
        "timestamp_finished": 1714163062343.071
    },
    "UNFIUSDT": {
        "adg_per_exposure_long": 0.00011657890049954212,
        "adg_per_exposure_short": 0.0,
        "adg_weighted_per_exposure_long": 0.00011657890049954212,
        "adg_weighted_per_exposure_short": 0.0,
        "drawdown_1pct_worst_mean_long": 0.4545397252787709,
        "drawdown_1pct_worst_mean_short": -0.0,
        "drawdown_max_long": 0.5381086454443261,
        "drawdown_max_short": -0.0,
        "exposure_ratios_mean_long": 0.23355030617250927,
        "exposure_ratios_mean_short": 0.0,
        "hrs_stuck_max_long": 133.51666666666668,
        "hrs_stuck_max_short": NaN,
        "loss_profit_ratio_long": 0.950589962167992,
        "loss_profit_ratio_short": 1.0,
        "n_days": 472.9583333333333,
        "pa_distance_1pct_worst_mean_long": 0.40276193823652984,
        "pa_distance_1pct_worst_mean_short": 100.0,
        "pa_distance_max_long": 0.4204749174935907,
        "pa_distance_max_short": 100.0,
        "pa_distance_mean_long": 0.0591133810067501,
        "pa_distance_mean_short": 100.0,
        "pa_distance_std_long": 0.07024545892668879,
        "pa_distance_std_short": 1.0,
        "sharpe_ratio_long": 0.001392826762908352,
        "sharpe_ratio_short": 0.0,
        "starting_balance": 10000.0,
        "time_at_max_exposure_long": 0.1712237721649387,
        "time_at_max_exposure_short": 0.0,
        "timestamp_finished": 1714163062343.072
    },
    "WAVESUSDT": {
        "adg_per_exposure_long": 0.001093246045196894,
        "adg_per_exposure_short": 0.0,
        "adg_weighted_per_exposure_long": 0.001093246045196894,
        "adg_weighted_per_exposure_short": 0.0,
        "drawdown_1pct_worst_mean_long": 0.06372460352479184,
        "drawdown_1pct_worst_mean_short": -0.0,
        "drawdown_max_long": 0.12713486676271607,
        "drawdown_max_short": -0.0,
        "exposure_ratios_mean_long": 0.053381066165304115,
        "exposure_ratios_mean_short": 0.0,
        "hrs_stuck_max_long": 239.73333333333332,
        "hrs_stuck_max_short": NaN,
        "loss_profit_ratio_long": 0.009809444214048068,
        "loss_profit_ratio_short": 1.0,
        "n_days": 472.9583333333333,
        "pa_distance_1pct_worst_mean_long": 0.0719294142080524,
        "pa_distance_1pct_worst_mean_short": 100.0,
        "pa_distance_max_long": 0.09441199674665064,
        "pa_distance_max_short": 100.0,
        "pa_distance_mean_long": 0.013885632636161934,
        "pa_distance_mean_short": 100.0,
        "pa_distance_std_long": 0.01149823955741899,
        "pa_distance_std_short": 1.0,
        "sharpe_ratio_long": 0.20718063545742224,
        "sharpe_ratio_short": 0.0,
        "starting_balance": 10000.0,
        "time_at_max_exposure_long": 0.007830957283874632,
        "time_at_max_exposure_short": 0.0,
        "timestamp_finished": 1714163062343.056
    },
    "WOOUSDT": {
        "adg_per_exposure_long": 0.0010989212262226822,
        "adg_per_exposure_short": 0.0,
        "adg_weighted_per_exposure_long": 0.0010989212262226822,
        "adg_weighted_per_exposure_short": 0.0,
        "drawdown_1pct_worst_mean_long": 0.14303772969424472,
        "drawdown_1pct_worst_mean_short": -0.0,
        "drawdown_max_long": 0.23718649343847575,
        "drawdown_max_short": -0.0,
        "exposure_ratios_mean_long": 0.09062830366462118,
        "exposure_ratios_mean_short": 0.0,
        "hrs_stuck_max_long": 163.3,
        "hrs_stuck_max_short": NaN,
        "loss_profit_ratio_long": 0.05084511710872802,
        "loss_profit_ratio_short": 1.0,
        "n_days": 472.9583333333333,
        "pa_distance_1pct_worst_mean_long": 0.156868940852188,
        "pa_distance_1pct_worst_mean_short": 100.0,
        "pa_distance_max_long": 0.20654620311277724,
        "pa_distance_max_short": 100.0,
        "pa_distance_mean_long": 0.019022385452578467,
        "pa_distance_mean_short": 100.0,
        "pa_distance_std_long": 0.02101099779460532,
        "pa_distance_std_short": 1.0,
        "sharpe_ratio_long": 0.06874978581646184,
        "sharpe_ratio_short": 0.0,
        "starting_balance": 10000.0,
        "time_at_max_exposure_long": 0.025783120170945823,
        "time_at_max_exposure_short": 0.0,
        "timestamp_finished": 1714163062343.061
    }
}